LICENSE
netcleanser/__init__.py
netcleanser/email.py
netcleanser/url.py
netcleanser-0.2.3.dist-info/LICENSE
netcleanser-0.2.3.dist-info/WHEEL
netcleanser-0.2.3.dist-info/METADATA
netcleanser-0.2.3.dist-info/RECORD
