Metadata-Version: 2.1
Name: netcleanser
Version: 0.2.3
Summary: The library makes parsing and manipulation of URL🌐 and Email address📧 easy.
Home-page: https://github.com/y-bar/netcleanser
License: MIT
Author: Shinichi Takayanagi
Author-email: shinichi.takayanagi@gmail.com
Requires-Python: >=3.7,<4.0
Classifier: License :: OSI Approved :: MIT License
Classifier: Programming Language :: Python :: 3
Classifier: Programming Language :: Python :: 3.7
Classifier: Programming Language :: Python :: 3.8
Classifier: Programming Language :: Python :: 3.9
Classifier: Topic :: Utilities
Requires-Dist: loguru (>=0.5.3,<0.6.0)
Requires-Dist: purl (>=1.6,<2.0)
Requires-Dist: requests (>=2.25.1,<3.0.0)
Requires-Dist: tldextract (>=3.1.0,<4.0.0)
Project-URL: Repository, https://github.com/y-bar/netcleanser
